{
  "generated": "2025-12-31T14:13:56Z",
  "streams": {
    "stable": {
      "tag": null,
      "name": null,
      "message": "No stable release yet. Please use beta or dev.",
      "release_url": "https://github.com/JanLahmann/RasQberry-Two/releases"
    },
    "beta": {
      "tag": "beta-2025-12-30-211449",
      "name": "rasqberry-beta-2025-12-30",
      "image_url": "https://github.com/JanLahmann/RasQberry-Two/releases/download/beta-2025-12-30-211449/rasqberry-beta-2025-12-30.img.xz",
      "release_url": "https://github.com/JanLahmann/RasQberry-Two/releases/tag/beta-2025-12-30-211449",
      "release_date": "2025-12-30",
      "image_download_size": 1668208604,
      "extract_size": 8866758656,
      "extract_sha256": "5830bc6a22020b3095d3b50612df650c54caefad61adfe39ab9515e9c9e122b7",
      "highlights": [
        "Quantum Paradoxes - 14 interactive notebooks with Qiskit 2.x compatibility",
        "Fun-with-Quantum - Quantum Coin Game, GHZ Game, Grover's Algorithm",
        "Virtual LED Display - Demo mode without physical hardware",
        "Touch Mode - Kiosk-friendly interface with on-screen keyboard",
        "IBM Quantum Tutorials - Desktop shortcuts and credentials notebook",
        "ARM64 Native Builds - Faster CI with native ARM runners + wheel cache",
        "XZ Compression - Smaller images (~30% reduction)"
      ]
    },
    "dev": {
      "tag": "dev-ab01-2025-12-31-145049",
      "name": "rasqberry-dev-ab01-2025-12-31-145049",
      "image_url": "https://github.com/JanLahmann/RasQberry-Two/releases/download/dev-ab01-2025-12-31-145049/rasqberry-dev-ab01-2025-12-31-145049.img.xz",
      "release_url": "https://github.com/JanLahmann/RasQberry-Two/releases/tag/dev-ab01-2025-12-31-145049",
      "release_date": "2025-12-31 14:50",
      "image_download_size": 1969953100,
      "extract_size": 8841592832,
      "extract_sha256": "a02eac6b12456d8b67518d0a7b5183854aca885db76d1ae3447d1217c80afa28",
      "highlights": [
        "update AB boot validation with all fixes applied"
      ]
    }
  }
}