{
  "imager": {
    "latest_version": "1.8.5",
    "url": "https://www.raspberrypi.com/software/"
  },
  "os_list": [
    {
      "name": "RasQberry Two Beta (64-bit)",
      "description": "Beta release with new features for testing",
      "icon": "https://rasqberry.org/Artwork/RasQberry 2 Logo Cube 64x64.png",
      "url": "https://github.com/JanLahmann/RasQberry-Two/releases/download/beta-2025-12-30-211449/rasqberry-beta-2025-12-30.img.xz",
      "extract_size": 8866758656,
      "extract_sha256": "5830bc6a22020b3095d3b50612df650c54caefad61adfe39ab9515e9c9e122b7",
      "image_download_size": 1668208604,
      "release_date": "2025-12-30",
      "init_format": "systemd",
      "devices": [
        "pi5-64bit",
        "pi4-64bit"
      ],
      "website": "https://rasqberry.org"
    },
    {
      "name": "RasQberry Two Dev (64-bit)",
      "description": "Development integration branch with latest features",
      "icon": "https://rasqberry.org/Artwork/RasQberry 2 Logo Cube 64x64.png",
      "url": "https://github.com/JanLahmann/RasQberry-Two/releases/download/development-2025-12-31-113832/rasqberry-development-2025-12-31-113832.img.xz",
      "extract_size": 8841592832,
      "extract_sha256": "f31ebb1cdb7e2d0972e8da41292164e7825be1e385f36b39e8bde194636b7bc6",
      "image_download_size": 1989503604,
      "release_date": "2025-12-31 11:38",
      "init_format": "systemd",
      "devices": [
        "pi5-64bit",
        "pi4-64bit"
      ],
      "website": "https://rasqberry.org"
    },
    {
      "name": "RasQberry Development Images",
      "description": "Development builds with cutting-edge features (unstable)",
      "icon": "https://rasqberry.org/Artwork/RasQberry 2 Logo Cube 64x64.png",
      "subitems": [
        {
          "name": "RasQberry Two Dev (dev-demojson228 2025-12-31-145514)",
          "description": "Development build from dev-demojson228",
          "icon": "https://rasqberry.org/Artwork/RasQberry 2 Logo Cube 64x64.png",
          "url": "https://github.com/JanLahmann/RasQberry-Two/releases/download/dev-demojson228-2025-12-31-145514/rasqberry-dev-demojson228-2025-12-31-145514.img.xz",
          "extract_size": 8841592832,
          "extract_sha256": "9ad9e4c92daa6a7977d05aa8ed86ce45c47923ee5c72999376b7862a476396b5",
          "image_download_size": 1990948404,
          "release_date": "2025-12-31 14:55",
          "init_format": "systemd",
          "devices": [
            "pi5-64bit",
            "pi4-64bit"
          ],
          "website": "https://rasqberry.org"
        },
        {
          "name": "RasQberry Two Dev (dev-ab01 2025-12-31-145049)",
          "description": "Development build from dev-ab01",
          "icon": "https://rasqberry.org/Artwork/RasQberry 2 Logo Cube 64x64.png",
          "url": "https://github.com/JanLahmann/RasQberry-Two/releases/download/dev-ab01-2025-12-31-145049/rasqberry-dev-ab01-2025-12-31-145049.img.xz",
          "extract_size": 8841592832,
          "extract_sha256": "a02eac6b12456d8b67518d0a7b5183854aca885db76d1ae3447d1217c80afa28",
          "image_download_size": 1969953100,
          "release_date": "2025-12-31 14:50",
          "init_format": "systemd",
          "devices": [
            "pi5-64bit",
            "pi4-64bit"
          ],
          "website": "https://rasqberry.org"
        },
        {
          "name": "RasQberry Two Dev (dev-gui01 2025-12-31-134807)",
          "description": "Development build from dev-gui01",
          "icon": "https://rasqberry.org/Artwork/RasQberry 2 Logo Cube 64x64.png",
          "url": "https://github.com/JanLahmann/RasQberry-Two/releases/download/dev-gui01-2025-12-31-134807/rasqberry-dev-gui01-2025-12-31-134807.img.xz",
          "extract_size": 8841592832,
          "extract_sha256": "9c405bee496c373a86a377ce3e169146f5d70bc851f9ef1e161691ce119e46ed",
          "image_download_size": 1991072572,
          "release_date": "2025-12-31 13:48",
          "init_format": "systemd",
          "devices": [
            "pi5-64bit",
            "pi4-64bit"
          ],
          "website": "https://rasqberry.org"
        },
        {
          "name": "RasQberry Two Dev (dev-install 2025-12-31-100911)",
          "description": "Development build from dev-install",
          "icon": "https://rasqberry.org/Artwork/RasQberry 2 Logo Cube 64x64.png",
          "url": "https://github.com/JanLahmann/RasQberry-Two/releases/download/dev-install-2025-12-31-100911/rasqberry-dev-install-2025-12-31-100911.img.xz",
          "extract_size": 8841592832,
          "extract_sha256": "c3b0995e9b767c0bc9ef2eff29985d8fc88d844ad2c9e5101b875ceb8fd5525f",
          "image_download_size": 1989614192,
          "release_date": "2025-12-31 10:09",
          "init_format": "systemd",
          "devices": [
            "pi5-64bit",
            "pi4-64bit"
          ],
          "website": "https://rasqberry.org"
        }
      ]
    },
    {
      "name": "RasQberry A/B Boot Images",
      "description": "Images with A/B partition support for safer updates (experimental)",
      "icon": "https://rasqberry.org/Artwork/RasQberry 2 Logo Cube 64x64.png",
      "subitems": [
        {
          "name": "RasQberry Two A/B (dev-demojson228 2025-12-31-145514)",
          "description": "A/B boot image from dev-demojson228",
          "icon": "https://rasqberry.org/Artwork/RasQberry 2 Logo Cube 64x64.png",
          "url": "https://github.com/JanLahmann/RasQberry-Two/releases/download/dev-demojson228-2025-12-31-145514/rasqberry-dev-demojson228-2025-12-31-145514-ab.img.xz",
          "extract_size": 12398362624,
          "extract_sha256": "c3a29546abe4d645f970bea511a201d76e41a5159162f7289d545fb4993ae811",
          "image_download_size": 2027608108,
          "release_date": "2025-12-31 14:55",
          "init_format": "systemd",
          "devices": [
            "pi5-64bit",
            "pi4-64bit"
          ],
          "website": "https://rasqberry.org"
        },
        {
          "name": "RasQberry Two A/B (dev-ab01 2025-12-31-145049)",
          "description": "A/B boot image from dev-ab01",
          "icon": "https://rasqberry.org/Artwork/RasQberry 2 Logo Cube 64x64.png",
          "url": "https://github.com/JanLahmann/RasQberry-Two/releases/download/dev-ab01-2025-12-31-145049/rasqberry-dev-ab01-2025-12-31-145049-ab.img.xz",
          "extract_size": 12398362624,
          "extract_sha256": "1234e4fd0d390c04410694b3b2a0fcd8f736f4b65c5b68e01fc1cd669a1ba551",
          "image_download_size": 2011507708,
          "release_date": "2025-12-31 14:50",
          "init_format": "systemd",
          "devices": [
            "pi5-64bit",
            "pi4-64bit"
          ],
          "website": "https://rasqberry.org"
        },
        {
          "name": "RasQberry Two A/B (dev-gui01 2025-12-31-134807)",
          "description": "A/B boot image from dev-gui01",
          "icon": "https://rasqberry.org/Artwork/RasQberry 2 Logo Cube 64x64.png",
          "url": "https://github.com/JanLahmann/RasQberry-Two/releases/download/dev-gui01-2025-12-31-134807/rasqberry-dev-gui01-2025-12-31-134807-ab.img.xz",
          "extract_size": 12398362624,
          "extract_sha256": "e7181437e8186ad73559dfc6c3755aa666014637f25842a240fcc8f8425254a4",
          "image_download_size": 2030618548,
          "release_date": "2025-12-31 13:48",
          "init_format": "systemd",
          "devices": [
            "pi5-64bit",
            "pi4-64bit"
          ],
          "website": "https://rasqberry.org"
        },
        {
          "name": "RasQberry Two A/B (development 2025-12-31-113832)",
          "description": "A/B boot image from development",
          "icon": "https://rasqberry.org/Artwork/RasQberry 2 Logo Cube 64x64.png",
          "url": "https://github.com/JanLahmann/RasQberry-Two/releases/download/development-2025-12-31-113832/rasqberry-development-2025-12-31-113832-ab.img.xz",
          "extract_size": 12398362624,
          "extract_sha256": "03abd15c8727a2be50f807271fef53c33a8c4e7a0cc5aaee0191d86675e445c7",
          "image_download_size": 2029400428,
          "release_date": "2025-12-31 11:38",
          "init_format": "systemd",
          "devices": [
            "pi5-64bit",
            "pi4-64bit"
          ],
          "website": "https://rasqberry.org"
        },
        {
          "name": "RasQberry Two A/B (dev-install 2025-12-31-100911)",
          "description": "A/B boot image from dev-install",
          "icon": "https://rasqberry.org/Artwork/RasQberry 2 Logo Cube 64x64.png",
          "url": "https://github.com/JanLahmann/RasQberry-Two/releases/download/dev-install-2025-12-31-100911/rasqberry-dev-install-2025-12-31-100911-ab.img.xz",
          "extract_size": 12398362624,
          "extract_sha256": "045f884373545bcf1f0114b9e4cca48d299f3ae6ccab63529a586cd850905a44",
          "image_download_size": 2029625716,
          "release_date": "2025-12-31 10:09",
          "init_format": "systemd",
          "devices": [
            "pi5-64bit",
            "pi4-64bit"
          ],
          "website": "https://rasqberry.org"
        },
        {
          "name": "RasQberry Two A/B (beta 2025-12-30)",
          "description": "A/B boot image from beta",
          "icon": "https://rasqberry.org/Artwork/RasQberry 2 Logo Cube 64x64.png",
          "url": "https://github.com/JanLahmann/RasQberry-Two/releases/download/beta-2025-12-30-211449/rasqberry-beta-2025-12-30-ab.img.xz",
          "extract_size": 12398362624,
          "extract_sha256": "d035a6672a3b8e4b2c8b82b6d42ecaeddfc271f4548960c4dcc9e5b3d6212e15",
          "image_download_size": 1639401356,
          "release_date": "2025-12-30",
          "init_format": "systemd",
          "devices": [
            "pi5-64bit",
            "pi4-64bit"
          ],
          "website": "https://rasqberry.org"
        }
      ]
    },
    {
      "name": "Raspberry Pi OS (64-bit)",
      "description": "A port of Debian Trixie with the Raspberry Pi Desktop (Recommended)",
      "icon": "https://downloads.raspberrypi.com/raspios_armhf/Raspberry_Pi_OS_(32-bit).png",
      "url": "https://downloads.raspberrypi.com/raspios_arm64/images/raspios_arm64-2025-12-04/2025-12-04-raspios-trixie-arm64.img.xz",
      "extract_size": 6450839552,
      "extract_sha256": "19b108fe07cff2b5cd7df0f76b6d7325e43fb2a1d5418d10f6bd56642e0e8579",
      "image_download_size": 1327702860,
      "release_date": "2025-12-04",
      "init_format": "cloudinit-rpi",
      "devices": [
        "pi5-64bit",
        "pi4-64bit",
        "pi3-64bit"
      ]
    }
  ]
}